generic_scpi_driver/__init__.py
generic_scpi_driver/driver.py
generic_scpi_driver/generic_aqctl.py
generic_scpi_driver/session.py
generic_scpi_driver/visa_session.py
generic_scpi_driver-1.8.dist-info/METADATA
generic_scpi_driver-1.8.dist-info/WHEEL
generic_scpi_driver-1.8.dist-info/licenses/LICENSE
generic_scpi_driver-1.8.dist-info/RECORD
