Metadata-Version: 2.4
Name: generic-scpi-driver
Version: 1.8
Summary: A generic template for creating python object-based drivers for SCPI hardware devices which communicate via VISA. Compatible with ARTIQ  installed with [artiq] modifier
License-File: LICENSE
Author: Charles Baynham
Author-email: charles.baynham@gmail.com
Requires-Python: >=3.10,<4.0
Classifier: Programming Language :: Python :: 3
Classifier: Programming Language :: Python :: 3.10
Classifier: Programming Language :: Python :: 3.11
Classifier: Programming Language :: Python :: 3.12
Classifier: Programming Language :: Python :: 3.13
Classifier: Programming Language :: Python :: 3.14
Requires-Dist: pyserial (>=3,<4)
Requires-Dist: pyvisa (>=1,<2)
Requires-Dist: pyvisa-py (>=0.7.0,<0.8.0)
